pymesa_web/__init__.py
pymesa_web/_version.py
pymesa_web-1.0.dist-info/METADATA
pymesa_web-1.0.dist-info/WHEEL
pymesa_web-1.0.dist-info/licenses/COPYING
pymesa_web-1.0.dist-info/licenses/LICENSE
pymesa_web-1.0.dist-info/RECORD
